LICENSE
MANIFEST.in
README.rst
VERSION
flask_restful_routing.py
setup.cfg
setup.py
flask_restful_routing.egg-info/PKG-INFO
flask_restful_routing.egg-info/SOURCES.txt
flask_restful_routing.egg-info/dependency_links.txt
flask_restful_routing.egg-info/not-zip-safe
flask_restful_routing.egg-info/top_level.txt