Metadata-Version: 1.1
Name: flask-restful-routing
Version: 1.0.3
Summary: An easier way to register flask-restful routes
Home-page: https://github.com/twopicode/flask-restful-routing
Author: Nick Whyte
Author-email: nick@nickwhyte.com
License: UNKNOWN
Platform: UNKNOWN
Classifier: Intended Audience :: Developers
Classifier: Programming Language :: Python
